{
    "authors": [
        "https://www.gmodstore.com/users/76561198392047603"
    ],
    "icon": "flags16/fr.png",

    "chat_no_permission": "Tu n'as pas le droit de faire ça.",
    "net_cooldown": "Vous envoyez trop de paquets au serveur, veuillez patienter et réessayer.",
    "error": "On dirait que quelque chose ne va pas. Réessayez ultérieurement.",

    "admin_permissions_saved": "Vos nouvelles permissions ont bien été enregistrées.",
    "admin_config_saved": "Votre configuration a été enregistrée avec succès.",

    "admin_preset_added": "Un nouveau préréglage a été ajouté avec succès.",
    "admin_preset_nope": "Votre préréglage manque d'informations.",
    "admin_preset_dupe": "Un préréglage avec ce nom existe déjà.",
    "admin_preset_cantfind": "Ce préréglage ne peut pas être trouvé.",
    "admin_preset_removed": "Préréglage supprimé.",
    "admin_preset_limit": "Vous ne pouvez pas avoir plus de 32 préréglages.",

    "admin_player_warned": "%s averti avec succès.",
    "admin_player_note_update": "Note Admin du joueur mise à jour avec succès.",
    "admin_player_wipewarns": "Tous les avertissements de %s ont été supprimé avec succès.",
    "admin_player_joinwithactive": "%s a rejoint le serveur avec %s points actifs.",

    "admin_punishment_created": "Santion créée.",
    "admin_punishment_removed": "Santion supprimée.",
    "admin_punishment_edited": "Sanction éditée.",

    "player_warn_notice": "%s vous a mis un avertissement, pour la raison suivante: %s",
    "player_warn_broadcast": "%s a été averti par %s pour la raison suivante: %s",
    "player_warn_immune": "Ce joueur est immunisé contre les avertissements.",
    "player_warn_noreason": "Veuillez spécifier une raison d'avertir ce joueur.",
    "player_warn_toolong": "Votre raison ne peut pas être plus longue de 150 caractères.",
    "player_warn_maxpoints": "Vous ne pouvez mettre au maximum %s points pour un avertissement.",
    "player_warn_help": "Pour avertir un joueur avec le tchat, utilisez: !warn <joueur> <quantité de point> <raison>",
    "player_warn_help_console": "Pour avertir un joueur via la console, utilisez : yaws warn <joueur> <quantité de points> <raison>",
    "player_warn_searchid_wait": "Buscando... por favor espere...",
    "player_warn_searchid_nonefound": "Aucun avertissement avec cet ID n'a été trouvé.",
    "player_warn_ui": "Vous ne pouvez pas avertir avec le tchat puisque vous n'avez que la permission d'utiliser les préréglages.",
    "player_warn_not_found": "Impossible de trouver le joueur \"%s\".",
    "player_warn_wrongpoints": "Le nombre de point spécifié est invalide.",
    "player_warn_notyou": "Vous ne pouvez pas vous avertir vous-même.",
    "player_warn_deleted": "Avertissement supprimé avec succès.",
    "player_warn_deleted_user": "%s a supprimé l'un de vos avertissements.",

    "generic_save": "Sauvegarder les changements",
    "generic_cancel": "Quitter",
    "generic_back": "Retour",
    "generic_point_count": "Nombre de Point",
    "generic_delete": "Supprimer",
    "generic_warned": "AVERTI",

    "sidebar_warnings": "Avertissements",
    "sidebar_players": "Joueurs",
    "sidebar_admin": "Admin",
    "sidebar_settings": "Paramètres",
    "sidebar_close": "Fermer",

    "players_tab_search": "Rechercher par nom/steamid(64).",
    "players_tab_search_button": "Rechercher",
    "players_tab_offline": "Rechercher les joueurs hors-ligne?",

    "viewing_player_no_warns_found": "Aucun avertissement n'a été trouvé pour ce joueur.",
    "viewing_player_action_submit_warn": "Soumettre un Nouvel Avertissement",
    "viewing_player_action_view_notes": "Voir les Notes Admin",
    "viewing_player_player_notes": "Notes Admin",
    "viewing_player_save_player_notes": "Sauvegarder les Notes Admin",

    "viewing_player_table_admin": "Admin",
    "viewing_player_table_reason": "Raison",
    "viewing_player_table_time": "Temps",
    "viewing_player_table_points": "Points",
    "viewing_player_table_server": "Serveur",

    "viewing_player_table_right_admin": "Copier Admin",
    "viewing_player_table_right_reason": "Copier Raison",
    "viewing_player_table_right_time": "Copier Temps",
    "viewing_player_table_right_points": "Copier Points Ajoutés",
    "viewing_player_table_right_server": "Copier Nom du Serveur",
    "viewing_player_table_right_log": "Copier comme Log",

    "viewing_player_wipe_header": "Supprimer tous les avertissements de %s ?",
    "viewing_player_wipe_subtext": "C'est irréversible. Veillez à être sûr que c'est bien ce que vous voulez faire",

    "viewing_warn_time": "Temps",
    "viewing_warn_point": "Point de Pénalité",
    "viewing_warn_server": "Serveur",
    "viewing_warn_reason": "Raison",

    "warn_player_submit": "Avertir le Joueur",
    "warn_player_reason": "Raison d'avertir",

    "admin_tab_sidebar_permissions": "Permissions",
    "admin_tab_sidebar_settings": "Paramètres",
    "admin_tab_sidebar_presets": "Préréglages",
    "admin_tab_sidebar_punishments": "Santions",

    "admin_tab_presets_none": "Aucun Préréglage n'a été trouvé",
    "admin_tab_presets_name": "Nom du Préréglage",
    "admin_tab_presets_reason": "Raison du Préréglage",
    "admin_tab_presets_create": "Créer le Préréglage",

    "admin_tab_punishments_selecttype": "Sélectionner le Type de Santion",
    "admin_tab_punishments_create": "Créer un Seuil de Sanction",
    "admin_tab_punishments_notype": "Aucun Type de Sanction sélectionné.",
    "admin_tab_punishments_none": "Aucune Sanction n'a été trouvée",

    "admin_tab_warning_presets_box": "Sélectionner un Préréglage",
    "admin_tab_warning_reason_placeholder": "Entrer une Raison",


    "yaws": "Yet Another Warning System",
    "context_warn": "Avertir ce Joueur",
    "context_presets": "Avertir ce Joueur utilisant les Préréglages",
    "context_points": "Nombre de point: %s",
    "context_reason": "Raison de l'Avertissement: %s",
    "context_submit": "Envoyer un Avertissement",
    "context_viewwarns": "Voir les Avertissements",
    "context_viewnotes": "Voir les Notes Admin",

    "points_format": "%s Points",

    "loading": "Chargement...",
    "loading_hehe": "Jouant à Satisfactory...",

    "permission_view_ui": "Ouvrir l'UI",
    "permission_view_self_warns": "Voir ses Propres Avertissements",
    "permission_view_others_warns": "Voir d'Autres Avertissements",
    "permission_view_admin_settings": "Voir et Modifier les Paramètres Admin",
    "permission_create_warns": "Créer des Avertissements",
    "permission_customise_reason": "Utiliser une Raison Personnalisée",
    "permission_delete_warns": "Supprimer les avertissements",

    "user_settings_darkmode_name": "Mode Sombre",
    "user_settings_darkmode_desc": "Active le Mode Sombre dans l'UI.",

    "user_settings_language_name": "Langage",
    "user_settings_language_desc": "En quelle langue voulez-vous que l'addon soit? Nécessite la réouverture de l'UI.",

    "user_settings_blur_name": "Arrière-plan flou",
    "user_settings_blur_desc": "Activez le flou sur l'arrière-plan de l'interface utilisateur. Nécessite la réouverture de l'interface utilisateur.",

    "admin_settings_prefix_name": "Préfixe",
    "admin_settings_prefix_desc": "Le préfixe que l'addon utilisera dans les messages du tchat.",

    "admin_settings_prefix_color_name": "Couleur du Préfixe",
    "admin_settings_prefix_color_desc": "La Couleur du Préfixe pour le tchat.",

    "admin_settings_broadcast_warns_name": "Avertissement pour tous",
    "admin_settings_broadcast_warns_desc": "Si oui, l'addon va avertir toutes les personnes en ligne.",

    "admin_settings_point_cooldown_time_name": "Durée des Points",
    "admin_settings_point_cooldown_time_desc": "Temps en secondes pour que les points actifs soient supprimés. Réglez sur 0 pour désactiver cela.",

    "admin_settings_point_cooldown_amount_name": "Durée du Temps de Recharge des Points",
    "admin_settings_point_cooldown_amount_desc": "Combien de points pour déduire chaque temps de recharge. Ne fera rien s'il est désactivé.",

    "admin_settings_reason_required_name": "Raison Requise?",
    "admin_settings_reason_required_desc": "Si oui, les admins devront préciser une raison pour tout avertissement.",

    "admin_settings_point_max_name": "Maximum de Points",
    "admin_settings_point_max_desc": "Le Nombre Maximum de Points qu'un Avertissement peut avoir.",

    "admin_settings_purge_on_punishment_name": "Purge de Sanction",
    "admin_settings_purge_on_punishment_desc": "Si oui, l'Addon marquera tous les Points d'un Joueur comme inactifs lorsqu'ils seront sanctionnés.",

    "admin_settings_join_message_enabled_name": "Message d'arrivée activé",
    "admin_settings_join_message_enabled_desc": "Si vrai, l'addon va envoyer un message aux joueurs quand ils rejoignent avec des points actifs.",

    "admin_settings_join_message_message_name": "Message d'arrivée",
    "admin_settings_join_message_message_desc": "Le message à envoyer. {active} sont les points actifs, {inactive} sont les points inactifs, {points} sont le total de points"

    "admin_settings_message_admins_on_active_join_name": "Prévient les Admins quand un joueur rejoint avec des points actifs",
    "admin_settings_message_admins_on_active_join_desc": "Envoie un message à tout ceux avec la permission \"Voir les Autres Avertissements\" quand un joueur rejoint avec des points actifs.",

    "admin_settings_category_points": "Points",
    "admin_settings_category_branding": "Branding",
    "admin_settings_category_warnings": "Avertissements"
}
